googlesearch/__init__.py
googlesearch/asearch.py
googlesearch/includes.py
googlesearch/user_agents.py
mi_googlesearch_python-1.3.0.post1.dist-info/LICENSE
mi_googlesearch_python-1.3.0.post1.dist-info/METADATA
mi_googlesearch_python-1.3.0.post1.dist-info/WHEEL
mi_googlesearch_python-1.3.0.post1.dist-info/top_level.txt
mi_googlesearch_python-1.3.0.post1.dist-info/RECORD
