Metadata-Version: 2.1
Name: mi-googlesearch-python
Version: 1.3.0.post1
Summary: A Python library for scraping the Google search engine.
Home-page: https://github.com/Nv7-GitHub/googlesearch
Author: Nishant Vikramaditya
Author-email: junk4Nv7@gmail.com
Classifier: Programming Language :: Python :: 3
Classifier: License :: OSI Approved :: MIT License
Classifier: Operating System :: OS Independent
Requires-Python: >=3.6
License-File: LICENSE
Requires-Dist: beautifulsoup4>=4.9
Requires-Dist: requests>=2.20
Requires-Dist: httpx
